asgimod/__init__.py
asgimod/db.py
asgimod/mixins.py
asgimod/sync.py
asgimod-0.1.1.dist-info/LICENSE
asgimod-0.1.1.dist-info/METADATA
asgimod-0.1.1.dist-info/WHEEL
asgimod-0.1.1.dist-info/top_level.txt
asgimod-0.1.1.dist-info/zip-safe
asgimod-0.1.1.dist-info/RECORD
