Metadata-Version: 2.1
Name: asgimod
Version: 0.1.1
Summary: Package to make Django *usable* in async Python
Home-page: https://github.com/paaksing/asgimod
Author: Paaksing
Author-email: paaksingtech@gmail.com
License: MIT
Keywords: Django,asyncio,async
Platform: UNKNOWN
Classifier: Development Status :: 5 - Production/Stable
Classifier: Programming Language :: Python :: 3.8
Classifier: Environment :: Web Environment
Classifier: Operating System :: OS Independent
Classifier: Intended Audience :: Developers
Classifier: License :: OSI Approved :: MIT License
Classifier: Topic :: Software Development :: Libraries :: Python Modules
Classifier: Natural Language :: English
Classifier: Framework :: Django :: 3.0
License-File: LICENSE
Requires-Dist: Django (>=3.0)
